BittyPro/Logic.v
module Logic(
        input  wire [15:0] in_a,
        input  wire [15:0] in_b,
        input  wire [3:0]  select,
        output reg  [15:0] alu_out
);
always @(*) begin
        case(select)
               4'd0: alu_out = in_a & in_b;
               4'd1: alu_out = ~(in_a & in_b);
               4'd2: alu_out = in_a | in_b;
               4'd3: alu_out = ~(in_a | in_b);
               4'd4: alu_out = in_a ^ in_b;
               4'd5: alu_out = in_a & ~in_b;
               4'd6: alu_out = in_a | ~in_b;
               4'd7: alu_out = ~in_a;
               default: alu_out = 0;
       endcase
end
endmodule

BittyPro/Arithmetic.v
module Arithmetic (
        input  wire        carry_in,
        input  wire [15:0] in_a,
        input  wire [15:0] in_b,
        input  wire [3:0]  select,
        output reg         carry_out,
        output wire        compare,
        output reg  [15:0] alu_out
);
always @(*) begin
       case(select)
               4'd0: begin
                       alu_out = 1;
                       carry_out = 0;
               end
               4'd1: begin
                       alu_out = in_a + (~16'b1) + ({15'b0, ~carry_in});
                       carry_out = (in_a > 16'b1) ? 1'b0 : 1'b1;
               end
               4'd2: begin
                       {carry_out, alu_out} = in_a + in_b + ({16'b0, carry_in});
               end
               4'd3: begin
                       alu_out = in_a + (~in_b) + ({15'b0, ~carry_in});
                       carry_out = (in_a > (in_b + ({15'b0, carry_in}))) ? 1'b0 : 1'b1;
               end
               4'd4: begin
                       alu_out = (in_a * in_b) + (~16'b1 + 1'b1);
                       carry_out = ((in_a * in_b) > 16'b1) ? 1'b0 : 1'b1;
               end
               4'd5: begin
                       alu_out = (in_a * ~in_b) + (~16'b1 + 1'b1);
                       carry_out = ((in_a * ~in_b) > 16'b1) ? 1'b0 : 1'b1;
               end
               4'd6: begin
                       {carry_out, alu_out} = in_a + in_a + ({16'b0, carry_in});
               end
               4'd7: begin
                       {carry_out, alu_out} = in_a + 1'b1 + ({16'b0, carry_in});
               end
               default: begin
                       alu_out = 0;
                       carry_out = 0;
               end
       endcase
end
assign compare = (in_a == in_b) ? 1'b1 : 1'b0;
endmodule

BittyPro/alu.v
module alu (
        input  wire        carry_in,
        input  wire [15:0] in_a,
        input  wire [15:0] in_b,
        input  wire [3:0]  select,
        input  wire        mode,
        output wire        carry_out,
        output wire        compare,
        output wire [15:0] alu_out
);
reg [15:0] alu_out1, alu_out2;
Arithmetic arith(carry_in, in_a, in_b, select, carry_out, compare, alu_out1);
Logic log (in_a, in_b, select, alu_out2);

assign alu_out = (mode) ? alu_out2 : alu_out1;
endmodule

BittyPro/controlunit.v
module controlunit (
	/* verilator lint_off UNUSED */
	input  reg [15:0]  inst,
	/* verilator lint_on UNUSED */
	input  reg         number,
        output wire [3:0]  sel,
        output wire        mode,
        output wire [2:0]  mux_sel
);
reg [2:0] mux_sel_reg;
always @(*) begin 
	if(number)
		mux_sel_reg = inst[15:13];
	else
		mux_sel_reg = inst[12:10];
end

assign sel = inst[5:2];
assign mode = inst[1];
assign mux_sel = mux_sel_reg;
endmodule

BittyPro/main.v
module main(
	/* verilator lint_off UNUSED */
	input  reg [15:0] inst,
	/* verilator lint_on UNUSED */
	input  reg [15:0] reg0,
        input  reg [15:0] reg1,
        input  reg [15:0] reg2,
        input  reg [15:0] reg3,
        input  reg [15:0] reg4,
        input  reg [15:0] reg5,
        input  reg [15:0] reg6,
        input  reg [15:0] reg7,
	output reg [15:0] out,
	output reg        cout,
	output reg        comp
);
reg [3:0] sel;
reg mode;
reg [2:0] mux_sel1, mux_sel2;

controlunit unit1 (inst, 1'b1, sel, mode, mux_sel1);
controlunit unit2 (inst, 1'b0, sel, mode, mux_sel2);

reg [15:0] A, B;

always @(*) begin
        case(mux_sel1)
                3'd0: A = reg0;
                3'd1: A = reg1;
                3'd2: A = reg2;
                3'd3: A = reg3;
                3'd4: A = reg4;
                3'd5: A = reg5;
                3'd6: A = reg6;
                3'd7: A = reg7;
        endcase
end

always @(*) begin
        case(mux_sel2)
                3'd0: B = reg0;
                3'd1: B = reg1;
                3'd2: B = reg2;
                3'd3: B = reg3;
                3'd4: B = reg4;
                3'd5: B = reg5;
                3'd6: B = reg6;
                3'd7: B = reg7;
        endcase
end

alu alu1(.carry_in(1'b0), .in_a(A), .in_b(B), .select(sel), .mode(mode), .carry_out(cout), .compare(comp), .alu_out(out));

endmodule

BittyPro/waveform.vcd
$version Generated by VerilatedVcd $end
$date Thu Apr 18 12:39:21 2024
 $end
$timescale   1ps $end

 $scope module TOP $end
  $var wire  1 4 comp $end
  $var wire  1 3 cout $end
  $var wire 16 ) inst [15:0] $end
  $var wire 16 2 out [15:0] $end
  $var wire 16 * reg0 [15:0] $end
  $var wire 16 + reg1 [15:0] $end
  $var wire 16 , reg2 [15:0] $end
  $var wire 16 - reg3 [15:0] $end
  $var wire 16 . reg4 [15:0] $end
  $var wire 16 / reg5 [15:0] $end
  $var wire 16 0 reg6 [15:0] $end
  $var wire 16 1 reg7 [15:0] $end
  $scope module main $end
   $var wire 16 % A [15:0] $end
   $var wire 16 & B [15:0] $end
   $var wire  1 4 comp $end
   $var wire  1 3 cout $end
   $var wire 16 ) inst [15:0] $end
   $var wire  1 $ mode $end
   $var wire  3 5 mux_sel1 [2:0] $end
   $var wire  3 6 mux_sel2 [2:0] $end
   $var wire 16 2 out [15:0] $end
   $var wire 16 * reg0 [15:0] $end
   $var wire 16 + reg1 [15:0] $end
   $var wire 16 , reg2 [15:0] $end
   $var wire 16 - reg3 [15:0] $end
   $var wire 16 . reg4 [15:0] $end
   $var wire 16 / reg5 [15:0] $end
   $var wire 16 0 reg6 [15:0] $end
   $var wire 16 1 reg7 [15:0] $end
   $var wire  4 # sel [3:0] $end
   $scope module alu1 $end
    $var wire 16 2 alu_out [15:0] $end
    $var wire 16 ' alu_out1 [15:0] $end
    $var wire 16 ( alu_out2 [15:0] $end
    $var wire  1 8 carry_in $end
    $var wire  1 3 carry_out $end
    $var wire  1 4 compare $end
    $var wire 16 % in_a [15:0] $end
    $var wire 16 & in_b [15:0] $end
    $var wire  1 $ mode $end
    $var wire  4 # select [3:0] $end
    $scope module arith $end
     $var wire 16 ' alu_out [15:0] $end
     $var wire  1 8 carry_in $end
     $var wire  1 3 carry_out $end
     $var wire  1 4 compare $end
     $var wire 16 % in_a [15:0] $end
     $var wire 16 & in_b [15:0] $end
     $var wire  4 # select [3:0] $end
    $upscope $end
    $scope module log $end
     $var wire 16 ( alu_out [15:0] $end
     $var wire 16 % in_a [15:0] $end
     $var wire 16 & in_b [15:0] $end
     $var wire  4 # select [3:0] $end
    $upscope $end
   $upscope $end
   $scope module unit1 $end
    $var wire 16 ) inst [15:0] $end
    $var wire  1 $ mode $end
    $var wire  3 5 mux_sel [2:0] $end
    $var wire  3 5 mux_sel_reg [2:0] $end
    $var wire  1 7 number $end
    $var wire  4 # sel [3:0] $end
   $upscope $end
   $scope module unit2 $end
    $var wire 16 ) inst [15:0] $end
    $var wire  1 $ mode $end
    $var wire  3 6 mux_sel [2:0] $end
    $var wire  3 6 mux_sel_reg [2:0] $end
    $var wire  1 8 number $end
    $var wire  4 # sel [3:0] $end
   $upscope $end
  $upscope $end
 $upscope $end
$enddefinitions $end


#0
b0000 #
0$
b0000000000000000 %
b0000000000000000 &
b0000000000000000 '
b0000000000000000 (
b0000000000000000 )
b0000000000000000 *
b0000000000000000 +
b0000000000000000 ,
b0000000000000000 -
b0000000000000000 .
b0000000000000000 /
b0000000000000000 0
b0000000000000000 1
b0000000000000000 2
03
04
b000 5
b000 6
17
08
#1
#2
#3
#4
#5
#6
#7
b0000000000000001 '
b0000000000000001 2
14
#8
#9
#10
#11
#12
#13
b1111 #
b0111000010000111 %
b0111100011100001 &
b0000000000000000 '
b0011110100111101 )
b0000110111011100 *
b0111000010000111 +
b0001101001110000 ,
b0101110111101001 -
b0100100000111110 .
b0101010010100001 /
b0100001001000001 0
b0111100011100001 1
b0000000000000000 2
04
b001 5
b111 6
#14
b0011 #
1$
b0100111000101010 %
b0101010000111011 &
b1111100111101111 '
b1010000111000100 (
b0101011110001111 )
b0010010000111000 *
b0101100001011100 +
b0100111000101010 ,
b0100001011101100 -
b0111110010110000 .
b0101010000111011 /
b0000011011111011 0
b0001101000110010 1
b1010000111000100 2
13
b010 5
b101 6
#15
#16
#17
#18
#19
#20
#21
#22
#23
#24
#25
#26
#27
b1101 #
b0100010111111010 %
b0100010111111010 &
b0000000000000000 '
b0000000000000000 (
b0000001001110111 )
b0100010111111010 *
b0100101111001011 +
b0010100001101100 ,
b0111110100000101 -
b0110101010101100 .
b0101010010000110 /
b0111111000100001 0
b0111101000101011 1
b0000000000000000 2
03
14
b000 5
b000 6
#28
#29
#30
#31
#32
#33
#34
#35
#36
b0001 #
b0111011000111110 %
b0100101000000101 &
b0111011000111101 '
b1011110111111011 (
b0010101110000110 )
b0010110011000011 *
b0111011000111110 +
b0100101000000101 ,
b0000000011110001 -
b0101110111101100 .
b0010111011011001 /
b0110100001100111 0
b0100110000110011 1
b1011110111111011 2
04
b001 5
b010 6
#37
#38
b1101 #
0$
b0110111001111000 %
b0010110010111100 &
b0000000000000000 '
b0000000000000000 (
b0100000110110100 )
b0010110010111100 *
b0000010101000100 +
b0110111001111000 ,
b0010001011111010 -
b0100111101001001 .
b0110111101101001 /
b0000000011100110 0
b0111111000100011 1
b0000000000000000 2
b010 5
b000 6
#39
#40
#41
#42
#43
#44
#45
b0101 #
1$
b0011110110101101 %
b0110000001010001 &
b0101111010010101 '
b0001110110101100 (
b0110101001010111 )
b0110110101011001 *
b0110010111010011 +
b0110000001010001 ,
b0011110110101101 -
b0110111110101100 .
b0001011110000110 /
b0111001010010101 0
b0010110010000000 1
b0001110110101100 2
b011 5
b010 6
#46
b0000 #
0$
b0100011001111100 %
b0011110001100110 &
b0000000000000001 '
b0000010001100100 (
b0001011111000000 )
b0100011001111100 *
b0011001010111011 +
b0100110000100010 ,
b0111110011111100 -
b0100010111100100 .
b0011110001100110 /
b0101111111011010 0
b0101101001100001 1
b0000000000000001 2
b000 5
b101 6
