Verilator/lab01/Logic.v
module Logic(
        input  wire [15:0] in_a,
        input  wire [15:0] in_b,
        input  wire [2:0]  select,
        output reg  [15:0] alu_out
);
always @(*) begin
        case(select)
               3'd0: alu_out = in_a & in_b;
               3'd1: alu_out = ~(in_a & in_b);
               3'd2: alu_out = in_a | in_b;
               3'd3: alu_out = ~(in_a | in_b);
               3'd4: alu_out = in_a ^ in_b;
               3'd5: alu_out = in_a & ~in_b;
               3'd6: alu_out = in_a | ~in_b;
               3'd7: alu_out = ~in_a;
               default: alu_out = 0;
       endcase
end
endmodule

Verilator/draft/Arithmetic.v
module Arithmetic (
        input  wire        carry_in,
        input  wire [15:0] in_a,
        input  wire [15:0] in_b,
        input  wire [2:0]  select,
        output reg         carry_out,
        output wire        compare,
        output reg  [15:0] alu_out
);
always @(*) begin
       case(select)
               3'd0: begin
                       alu_out = 1;
                       carry_out = 0;
               end
               3'd1: begin
                       alu_out = in_a + (~16'b1) + ({15'b0, ~carry_in});
                       carry_out = (in_a > 16'b1) ? 1'b0 : 1'b1;
               end
               3'd2: begin
                       {carry_out, alu_out} = in_a + in_b + ({16'b0, carry_in});
               end
               3'd3: begin
                       alu_out = in_a + (~in_b) + ({15'b0, ~carry_in});
                       carry_out = (in_a > (in_b + ({15'b0, carry_in}))) ? 1'b0 : 1'b1;
               end
               3'd4: begin
                       alu_out = (in_a * in_b) + (~16'b1 + 1'b1);
                       carry_out = ((in_a * in_b) > 16'b1) ? 1'b0 : 1'b1;
               end
               3'd5: begin
                       alu_out = (in_a * ~in_b) + (~16'b1 + 1'b1);
                       carry_out = ((in_a * ~in_b) > 16'b1) ? 1'b0 : 1'b1;
               end
               3'd6: begin
                       {carry_out, alu_out} = in_a + in_a + ({16'b0, carry_in});
               end
               3'd7: begin
                       {carry_out, alu_out} = in_a + 1'b1 + ({16'b0, carry_in});
               end
               default: begin
                       alu_out = 0;
                       carry_out = 0;
               end
       endcase
end
assign compare = (in_a == in_b) ? 1'b1 : 1'b0;
endmodule

Verilator/lab01/alu.v
module alu (
        input  wire        carry_in,
        input  wire [15:0] in_a,
        input  wire [15:0] in_b,
        input  wire [2:0]  select,
        input  wire        mode,
        output wire        carry_out,
        output wire        compare,
        output wire [15:0] alu_out
);
reg [15:0] alu_out1, alu_out2;
Arithmetic arith(carry_in, in_a, in_b, select, carry_out, compare, alu_out1);
Logic log (in_a, in_b, select, alu_out2);

assign alu_out = (mode) ? alu_out2 : alu_out1;
endmodule

Verilator/lab01/waveform.vcd
$version Generated by VerilatedVcd $end
$date Sat Apr  6 16:53:55 2024
 $end
$timescale   1ps $end

 $scope module TOP $end
  $var wire 16 * alu_out [15:0] $end
  $var wire  1 # carry_in $end
  $var wire  1 ( carry_out $end
  $var wire  1 ) compare $end
  $var wire 16 $ in_a [15:0] $end
  $var wire 16 % in_b [15:0] $end
  $var wire  1 ' mode $end
  $var wire  3 & select [2:0] $end
  $scope module alu $end
   $var wire 16 * alu_out [15:0] $end
   $var wire 16 + alu_out1 [15:0] $end
   $var wire 16 , alu_out2 [15:0] $end
   $var wire  1 # carry_in $end
   $var wire  1 ( carry_out $end
   $var wire  1 ) compare $end
   $var wire 16 $ in_a [15:0] $end
   $var wire 16 % in_b [15:0] $end
   $var wire  1 ' mode $end
   $var wire  3 & select [2:0] $end
   $scope module arith $end
    $var wire 16 + alu_out [15:0] $end
    $var wire  1 # carry_in $end
    $var wire  1 ( carry_out $end
    $var wire  1 ) compare $end
    $var wire 16 $ in_a [15:0] $end
    $var wire 16 % in_b [15:0] $end
    $var wire  3 & select [2:0] $end
   $upscope $end
   $scope module log $end
    $var wire 16 , alu_out [15:0] $end
    $var wire 16 $ in_a [15:0] $end
    $var wire 16 % in_b [15:0] $end
    $var wire  3 & select [2:0] $end
   $upscope $end
  $upscope $end
 $upscope $end
$enddefinitions $end


#0
0#
b0000000000000000 $
b0000000000000000 %
b000 &
0'
0(
0)
b0000000000000000 *
b0000000000000000 +
b0000000000000000 ,
#1
#2
#3
#4
#5
#6
#7
1)
b0000000000000001 *
b0000000000000001 +
#8
#9
#10
b0000000000110100 $
b0000000000111000 %
b100 &
1'
0)
b0000000000001100 *
b0000101101011111 +
b0000000000001100 ,
#11
#12
#13
#14
b0000000000010011 $
b0000000000110011 %
0'
b0000001111001000 *
b0000001111001000 +
b0000000000100000 ,
#15
#16
#17
#18
#19
#20
#21
#22
1#
b0000000000011110 $
b0000000000000111 %
b111 &
1'
b1111111111100001 *
b0000000000100000 +
b1111111111100001 ,
#23
#24
#25
#26
#27
#28
#29
#30
#31
#32
#33
#34
#35
#36
#37
#38
#39
#40
0#
b0000000001001011 $
b0000000001011000 %
b011 &
0'
1(
b1111111111110011 *
b1111111111110011 +
b1111111110100100 ,
#41
#42
#43
#44
1#
b0000000000101100 $
b0000000000011000 %
b101 &
0(
b1111101110110011 *
b1111101110110011 +
b0000000000100100 ,
#45
#46
#47
b0000000000001111 $
b0000000000111010 %
b001 &
b0000000000001101 *
b0000000000001101 +
b1111111111110101 ,
#48
0#
b0000000000100110 $
b0000000001000101 %
b111 &
b0000000000100111 *
b0000000000100111 +
b1111111111011001 ,
#49
#50
#51
b0000000000011111 $
b0000000000011110 %
b010 &
b0000000000111101 *
b0000000000111101 +
b0000000000011111 ,
#52
#53
#54
#55
#56
#57
#58
1#
b0000000000100101 $
b0000000000001000 %
b100 &
b0000000100100111 *
b0000000100100111 +
b0000000000101101 ,
#59
#60
#61
#62
0#
b0000000000110110 $
b0000000001000001 %
b011 &
1'
1(
b1111111110001000 *
b1111111111110101 +
b1111111110001000 ,
#63
#64
#65
#66
#67
#68
#69
#70
1#
b0000000000010001 $
b0000000001010001 %
b001 &
0'
0(
b0000000000001111 *
b0000000000001111 +
b1111111111101110 ,
#71
#72
b0000000001011001 $
b0000000001011110 %
1'
b1111111110100111 *
b0000000001010111 +
b1111111110100111 ,
#73
#74
b0000000000010100 $
b0000000000011000 %
b000 &
b0000000000010000 *
b0000000000000001 +
b0000000000010000 ,
#75
#76
#77
b0000000000100000 $
b0000000000101110 %
0'
b0000000000000001 *
b0000000000100000 ,
#78
#79
#80
#81
#82
#83
b0000000000001101 $
b0000000000001011 %
b100 &
1'
b0000000000000110 *
b0000000010001110 +
b0000000000000110 ,
#84
#85
#86
#87
b0000000001010010 $
b0000000000011111 %
b011 &
b1111111110100000 *
b0000000000110010 +
b1111111110100000 ,
#88
#89
#90
#91
#92
0#
b0000000001000010 $
b0000000000111111 %
b100 &
0'
b0001000000111101 *
b0001000000111101 +
b0000000001111101 ,
#93
#94
#95
#96
#97
#98
#99
b0000000001011011 $
b0000000000000010 %
b111 &
1'
b1111111110100100 *
b0000000001011100 +
b1111111110100100 ,
#100
#101
1#
b0000000000100111 $
b0000000000010101 %
b010 &
b0000000000110111 *
b0000000000111101 +
b0000000000110111 ,
#102
#103
#104
0#
b0000000001001100 $
b0000000001011100 %
b111 &
b1111111110110011 *
b0000000001001101 +
b1111111110110011 ,
#105
#106
#107
#108
#109
#110
#111
#112
#113
#114
b0000000001010110 $
b0000000000101001 %
b000 &
b0000000000000000 *
b0000000000000001 +
b0000000000000000 ,
#115
#116
#117
#118
#119
#120
1#
b0000000001000011 $
b0000000000111100 %
b100 &
b0000000001111111 *
b0000111110110011 +
b0000000001111111 ,
#121
#122
0#
b0000000000111111 $
b0000000000101100 %
b010 &
b0000000000111111 *
b0000000001101011 +
b0000000000111111 ,
#123
#124
#125
#126
#127
#128
1#
b0000000001000011 $
b0000000000110011 %
b110 &
0'
b0000000010000111 *
b0000000010000111 +
b1111111111001111 ,
#129
#130
#131
#132
#133
0#
b0000000000111001 $
b0000000000000000 %
b101 &
1'
b0000000000111001 *
b1111111111000110 +
b0000000000111001 ,
#134
#135
b0000000000100111 $
b0000000000101000 %
b000 &
0'
b0000000000000001 *
b0000000000000001 +
b0000000000100000 ,
#136
#137
#138
b0000000000001011 $
b0000000001010011 %
b010 &
b0000000001011110 *
b0000000001011110 +
b0000000001011011 ,
#139
#140
#141
#142
1#
b0000000000000000 $
b0000000000100011 %
b011 &
1(
b1111111111011100 *
b1111111111011100 +
b1111111111011100 ,
#143
#144
#145
#146
#147
#148
0#
b0000000001000010 $
b0000000000001111 %
1'
0(
b1111111110110000 *
b0000000000110011 +
b1111111110110000 ,
#149
#150
#151
#152
#153
#154
#155
#156
b0000000000000100 $
b0000000000111100 %
b100 &
0'
b0000000011101111 *
b0000000011101111 +
b0000000000111000 ,
#157
b0000000000010000 $
b0000000000110101 %
b000 &
1'
b0000000000010000 *
b0000000000000001 +
b0000000000010000 ,
#158
b0000000001100011 $
b0000000000010000 %
b111 &
0'
b0000000001100100 *
b0000000001100100 +
b1111111110011100 ,
#159
#160
#161
#162
#163
#164
b0000000000001101 $
b0000000000001011 %
b101 &
1'
b0000000000000100 *
b1111111101100011 +
b0000000000000100 ,
#165
#166
#167
1#
b0000000001000000 $
b0000000001011100 %
b000 &
b0000000001000000 *
b0000000000000001 +
b0000000001000000 ,
#168
#169
0#
b0000000000111111 $
b0000000001000001 %
b111 &
0'
b0000000001000000 +
b1111111111000000 ,
#170
#171
#172
1#
b0000000000111001 $
b0000000000011101 %
b100 &
1'
b0000000000100100 *
b0000011001110100 +
b0000000000100100 ,
#173
0#
b0000000001000000 $
b0000000000111011 %
b000 &
0'
b0000000000000001 *
b0000000000000001 +
b0000000000000000 ,
#174
1#
b0000000000000010 $
b0000000000110000 %
#175
#176
#177
#178
b0000000001010011 $
b0000000000010100 %
b101 &
1'
b0000000001000011 *
b1111100100110000 +
b0000000001000011 ,
#179
#180
#181
b0000000001001100 $
b0000000000111001 %
b001 &
b1111111111110111 *
b0000000001001010 +
b1111111111110111 ,
#182
#183
0#
b0000000001000000 $
b0000000001001010 %
b011 &
0'
1(
b1111111111110110 *
b1111111111110110 +
b1111111110110101 ,
#184
#185
b0000000001010100 $
b0000000000100000 %
b101 &
1'
0(
b0000000001010100 *
b1111010100101011 +
b0000000001010100 ,
#186
#187
#188
#189
#190
#191
#192
#193
#194
#195
#196
#197
#198
#199
#200
#201
#202
#203
#204
#205
#206
#207
#208
#209
#210
#211
b0000000001011101 $
b0000000001011111 %
b000 &
b0000000001011101 *
b0000000000000001 +
b0000000001011101 ,
#212
1#
b0000000000001010 $
b0000000000101000 %
b001 &
0'
b0000000000001000 *
b0000000000001000 +
b1111111111110111 ,
#213
#214
#215
#216
#217
#218
#219
#220
b0000000000111110 $
b0000000000110000 %
b100 &
1'
b0000000000001110 *
b0000101110011111 +
b0000000000001110 ,
#221
#222
#223
0#
b0000000001010000 $
b0000000001010100 %
b000 &
0'
b0000000000000001 *
b0000000000000001 +
b0000000001010000 ,
#224
#225
b0000000001001111 $
b0000000001000111 %
b010 &
1'
b0000000001001111 *
b0000000010010110 +
b0000000001001111 ,
#226
#227
#228
#229
#230
#231
#232
b0000000000110101 $
b0000000000110001 %
b111 &
b1111111111001010 *
b0000000000110110 +
b1111111111001010 ,
#233
b0000000000101111 $
b0000000001011100 %
b1111111111010000 *
b0000000000110000 +
b1111111111010000 ,
#234
#235
#236
#237
#238
1#
b0000000000111011 $
b0000000000000100 %
b001 &
0'
b0000000000111001 *
b0000000000111001 +
b1111111111111111 ,
#239
#240
#241
#242
#243
#244
#245
#246
b0000000000110111 $
b0000000001011101 %
b110 &
b0000000001101111 *
b0000000001101111 +
b1111111110110111 ,
#247
0#
b0000000001010000 $
b0000000001000100 %
b000 &
1'
b0000000001000000 *
b0000000000000001 +
b0000000001000000 ,
#248
#249
1#
b0000000000111101 $
b0000000000011011 %
b001 &
b1111111111100110 *
b0000000000111011 +
b1111111111100110 ,
#250
b0000000000100110 $
b0000000001001001 %
b101 &
0'
b1111010100000011 *
b1111010100000011 +
b0000000000100110 ,
#251
b0000000001100011 $
b0000000000111011 %
b110 &
b0000000011000111 *
b0000000011000111 +
b1111111111100111 ,
#252
0#
b0000000001001110 $
b0000000000100000 %
b100 &
b0000100110111111 *
b0000100110111111 +
b0000000001101110 ,
#253
#254
#255
#256
#257
#258
#259
#260
1#
b0000000000111100 $
b0000000000100101 %
b000 &
1'
b0000000000100100 *
b0000000000000001 +
b0000000000100100 ,
#261
#262
#263
#264
#265
#266
#267
0#
b0000000000000110 $
b0000000000111100 %
b111 &
0'
b0000000000000111 *
b0000000000000111 +
b1111111111111001 ,
#268
#269
#270
#271
1#
b0000000000110100 $
b0000000000100010 %
b011 &
b0000000000010001 *
b0000000000010001 +
b1111111111001001 ,
#272
#273
#274
b0000000001011001 $
b0000000001001010 %
b110 &
b0000000010110011 *
b0000000010110011 +
b1111111111111101 ,
#275
#276
#277
0#
b0000000000010010 $
b0000000000000110 %
b001 &
1'
b1111111111111101 *
b0000000000010001 +
#278
#279
#280
#281
#282
#283
#284
#285
#286
#287
#288
#289
#290
b0000000000111111 $
b0000000000100011 %
0'
b0000000000111110 *
b0000000000111110 +
b1111111111011100 ,
#291
#292
#293
#294
#295
#296
#297
1#
b0000000000110111 $
b0000000000101001 %
1'
b1111111111011110 *
b0000000000110101 +
b1111111111011110 ,
#298
#299
#300
#301
#302
#303
#304
#305
b0000000000111100 $
b0000000001001011 %
b011 &
1(
b1111111110000000 *
b1111111111110000 +
b1111111110000000 ,
#306
#307
#308
#309
#310
#311
#312
#313
#314
0#
b0000000000100001 $
b0000000001011000 %
b101 &
0(
b0000000000100001 *
b1111010010000110 +
b0000000000100001 ,
#315
#316
#317
#318
#319
#320
#321
#322
#323
b0000000000000010 $
b0000000000111001 %
b110 &
0'
b0000000000000100 *
b0000000000000100 +
b1111111111000110 ,
#324
#325
#326
b0000000001010100 $
b0000000000001010 %
b011 &
1'
b1111111110100001 *
b0000000001001010 +
b1111111110100001 ,
#327
#328
#329
#330
#331
#332
#333
b0000000000010101 $
b0000000000100001 %
b001 &
b1111111111111110 *
b0000000000010100 +
b1111111111111110 ,
#334
#335
#336
#337
1#
b0000000000100101 $
b0000000001001110 %
b011 &
0'
1(
b1111111111010110 *
b1111111111010110 +
b1111111110010000 ,
#338
#339
#340
#341
#342
0#
b0000000000100001 $
b0000000000011100 %
b101 &
0(
b1111110001000010 *
b1111110001000010 +
b0000000000100001 ,
#343
#344
#345
#346
#347
#348
#349
#350
#351
#352
#353
#354
#355
#356
b0000000001000100 $
b100 &
b0000011101101111 *
b0000011101101111 +
b0000000001011000 ,
#357
#358
#359
1#
b0000000001100010 $
b0000000001001011 %
b111 &
1'
b1111111110011101 *
b0000000001100100 +
b1111111110011101 ,
#360
#361
0#
b0000000000100001 $
b0000000000110111 %
b001 &
0'
b0000000000100000 *
b0000000000100000 +
b1111111111011110 ,
#362
#363
b0000000000001111 $
b0000000000000011 %
b000 &
1'
b0000000000000011 *
b0000000000000001 +
b0000000000000011 ,
#364
#365
#366
b0000000000001010 $
b0000000000111001 %
b011 &
1(
b1111111111000100 *
b1111111111010001 +
b1111111111000100 ,
#367
1#
b0000000000011101 $
b0000000000111101 %
b110 &
0(
b1111111111011111 *
b0000000000111011 +
b1111111111011111 ,
#368
#369
#370
b0000000001000111 $
b0000000000000100 %
b101 &
0'
b1111111010011100 *
b1111111010011100 +
b0000000001000011 ,
#371
#372
b0000000001001101 $
b0000000001011000 %
b010 &
b0000000010100110 *
b0000000010100110 +
b0000000001011101 ,
#373
#374
#375
#376
#377
#378
#379
b0000000000100010 $
b0000000000101000 %
b0000000001001011 *
b0000000001001011 +
b0000000000101010 ,
#380
#381
#382
#383
0#
b0000000000100000 $
b0000000000101101 %
b110 &
1'
b1111111111110010 *
b0000000001000000 +
b1111111111110010 ,
#384
#385
#386
#387
#388
#389
#390
b0000000001000100 $
b0000000001001011 %
b011 &
0'
1(
b1111111111111001 *
b1111111111111001 +
b1111111110110000 ,
#391
#392
b0000000000110011 $
b0000000001000001 %
b110 &
1'
0(
b1111111110111111 *
b0000000001100110 +
b1111111110111111 ,
#393
#394
#395
#396
#397
#398
#399
#400
1#
b0000000000001100 $
b0000000001000100 %
b011 &
1(
b1111111110110011 *
b1111111111000111 +
b1111111110110011 ,
#401
#402
#403
#404
#405
#406
#407
#408
#409
#410
#411
#412
#413
0#
b0000000001011100 $
b0000000000011111 %
b010 &
0(
b0000000001011111 *
b0000000001111011 +
b0000000001011111 ,
#414
#415
#416
1#
b0000000001010100 $
b0000000000110110 %
b111 &
0'
b0000000001010110 *
b0000000001010110 +
b1111111110101011 ,
#417
b0000000001000000 $
b0000000000000000 %
b011 &
b0000000000111111 *
b0000000000111111 +
b1111111110111111 ,
#418
#419
#420
#421
#422
#423
#424
#425
#426
#427
#428
#429
#430
#431
#432
#433
#434
0#
b0000000001000110 $
b0000000000101000 %
b110 &
b0000000010001100 *
b0000000010001100 +
b1111111111010111 ,
#435
#436
#437
#438
#439
#440
#441
#442
1#
b0000000000110101 $
b0000000000001101 %
b111 &
1'
b1111111111001010 *
b0000000000110111 +
b1111111111001010 ,
#443
#444
0#
b0000000000100110 $
b0000000000111111 %
b1111111111011001 *
b0000000000100111 +
b1111111111011001 ,
#445
#446
#447
#448
#449
1#
b0000000000100011 $
b0000000001001111 %
0'
b0000000000100101 *
b0000000000100101 +
b1111111111011100 ,
#450
#451
#452
#453
#454
#455
#456
#457
#458
#459
#460
#461
#462
b0000000000001011 $
b0000000001100011 %
b110 &
1'
b1111111110011111 *
b0000000000010111 +
b1111111110011111 ,
#463
0#
b0000000000110001 $
b0000000000011010 %
b100 &
0'
b0000010011111001 *
b0000010011111001 +
b0000000000101011 ,
#464
b0000000001010001 $
b0000000000111011 %
b111 &
1'
b1111111110101110 *
b0000000001010010 +
b1111111110101110 ,
#465
b0000000000101110 $
b0000000001100001 %
b011 &
1(
b1111111110010000 *
b1111111111001101 +
b1111111110010000 ,
#466
#467
#468
#469
1#
b0000000000000000 $
b0000000000100100 %
b111 &
0'
0(
b0000000000000010 *
b0000000000000010 +
b1111111111111111 ,
#470
#471
#472
#473
#474
#475
b0000000001100100 $
b0000000000001101 %
b110 &
1'
b1111111111110110 *
b0000000011001001 +
b1111111111110110 ,
#476
#477
#478
#479
0#
b0000000000010010 $
b0000000000000010 %
b000 &
0'
b0000000000000001 *
b0000000000000001 +
b0000000000000010 ,
#480
#481
#482
b0000000000001010 $
b0000000001010011 %
b011 &
1'
1(
b1111111110100100 *
b1111111110110111 +
b1111111110100100 ,
#483
#484
#485
#486
#487
#488
#489
#490
b0000000001000110 $
b0000000000001111 %
0'
0(
b0000000000110111 *
b0000000000110111 +
b1111111110110000 ,
#491
b0000000001000111 $
b0000000001011001 %
b000 &
b0000000000000001 *
b0000000000000001 +
b0000000001000001 ,
#492
#493
#494
#495
1#
b0000000000101011 $
b0000000001011111 %
1'
b0000000000001011 *
b0000000000001011 ,
#496
#497
#498
#499
#500
#501
#502
#503
#504
#505
#506
#507
#508
b0000000001001001 $
b0000000001000011 %
b010 &
0'
b0000000010001101 *
b0000000010001101 +
b0000000001001011 ,
#509
#510
#511
#512
b0000000001000010 $
b0000000000111010 %
b001 &
b0000000001000000 *
b0000000001000000 +
b1111111111111101 ,
#513
#514
0#
b0000000001010110 $
b0000000000110110 %
b110 &
1'
b1111111111011111 *
b0000000010101100 +
b1111111111011111 ,
#515
#516
#517
#518
#519
#520
#521
#522
b0000000000101011 $
b0000000001010110 %
b101 &
0'
b1111000101100010 *
b1111000101100010 +
b0000000000101001 ,
#523
#524
1#
b0000000000101100 $
b0000000000101100 %
b001 &
1'
1)
b1111111111010011 *
b0000000000101010 +
b1111111111010011 ,
#525
#526
#527
b0000000001100100 $
b0000000001000011 %
b100 &
0)
b0000000000100111 *
b0001101000101011 +
b0000000000100111 ,
#528
#529
#530
#531
0#
b0000000000000000 $
b0000000001001001 %
b010 &
b0000000001001001 *
b0000000001001001 +
b0000000001001001 ,
#532
#533
b0000000000100110 $
b0000000001010001 %
b001 &
0'
b0000000000100101 *
b0000000000100101 +
b1111111111111111 ,
#534
b0000000001011100 $
b0000000000101110 %
b111 &
1'
b1111111110100011 *
b0000000001011101 +
b1111111110100011 ,
#535
#536
1#
b0000000000001000 $
b0000000000111010 %
b110 &
b1111111111001101 *
b0000000000010001 +
b1111111111001101 ,
#537
#538
#539
#540
#541
b0000000001011001 $
b0000000000001100 %
b001 &
b1111111111110111 *
b0000000001010111 +
b1111111111110111 ,
#542
#543
#544
0#
b0000000000100010 $
b0000000000000100 %
b100 &
0'
b0000000010000111 *
b0000000010000111 +
b0000000000100110 ,
#545
#546
#547
#548
#549
#550
#551
1#
b0000000001000011 $
b0000000000001010 %
b110 &
1'
b1111111111110111 *
b1111111111110111 ,
#552
b0000000000101011 $
b0000000000001011 %
b100 &
0'
b0000000111011000 *
b0000000111011000 +
b0000000000100000 ,
#553
#554
#555
#556
#557
#558
#559
#560
#561
#562
#563
#564
#565
#566
#567
#568
#569
b0000000000110111 $
b0000000000100111 %
b000 &
b0000000000000001 *
b0000000000000001 +
b0000000000100111 ,
#570
#571
#572
#573
#574
#575
#576
#577
#578
#579
#580
#581
#582
#583
#584
#585
#586
0#
b0000000001011010 $
b0000000001011011 %
b010 &
1'
b0000000001011011 *
b0000000010110101 +
b0000000001011011 ,
#587
#588
#589
#590
b0000000000101100 $
b0000000001010100 %
b001 &
0'
b0000000000101011 *
b0000000000101011 +
b1111111111111011 ,
#591
#592
#593
#594
1#
b0000000001001101 $
b0000000001001100 %
b000 &
1'
b0000000001001100 *
b0000000000000001 +
b0000000001001100 ,
#595
#596
b0000000000101110 $
b0000000000011010 %
b101 &
0'
b1111101100100101 *
b1111101100100101 +
b0000000000100100 ,
#597
#598
#599
#600
#601
#602
#603
0#
b0000000000010000 $
b0000000001010010 %
1'
b0000000000000000 *
b1111101011001111 +
b0000000000000000 ,
#604
#605
1#
b0000000001000001 $
b0000000000010011 %
b111 &
0'
b0000000001000011 *
b0000000001000011 +
b1111111110111110 ,
#606
#607
0#
b0000000000100110 $
b0000000000101001 %
b010 &
b0000000001001111 *
b0000000001001111 +
b0000000000101111 ,
#608
#609
#610
#611
1#
b0000000000011001 $
b0000000000001001 %
b111 &
1'
b1111111111100110 *
b0000000000011011 +
b1111111111100110 ,
#612
#613
#614
#615
#616
#617
#618
#619
#620
b0000000000011011 $
b0000000001100100 %
b011 &
0'
1(
b1111111110110110 *
b1111111110110110 +
b1111111110000000 ,
#621
#622
#623
#624
#625
#626
#627
#628
#629
#630
#631
#632
#633
#634
#635
#636
#637
#638
#639
#640
#641
#642
b0000000001100100 $
b0000000000010111 %
b110 &
1'
0(
b1111111111101100 *
b0000000011001001 +
b1111111111101100 ,
#643
b0000000001100011 $
b0000000000010001 %
b101 &
0'
b1111100100001001 *
b1111100100001001 +
b0000000001100010 ,
#644
#645
#646
#647
#648
#649
0#
b0000000001100000 $
b0000000000110100 %
b111 &
1'
b1111111110011111 *
b0000000001100001 +
b1111111110011111 ,
#650
#651
#652
#653
#654
#655
#656
1#
b0000000000011001 $
b0000000001000000 %
b000 &
0'
b0000000000000001 *
b0000000000000001 +
b0000000000000000 ,
#657
#658
b0000000000111011 $
b0000000000111000 %
b011 &
1'
b1111111111000100 *
b0000000000000010 +
b1111111111000100 ,
#659
#660
#661
#662
#663
#664
#665
#666
#667
#668
#669
#670
#671
#672
0#
b0000000001000011 $
b0000000001010011 %
b010 &
b0000000001010011 *
b0000000010010110 +
b0000000001010011 ,
#673
#674
#675
#676
#677
#678
#679
#680
#681
1#
b0000000000010110 $
b0000000000000010 %
b001 &
b1111111111111101 *
b0000000000010100 +
b1111111111111101 ,
#682
#683
#684
b0000000000101011 $
b0000000000100010 %
b100 &
0'
b0000010110110101 *
b0000010110110101 +
b0000000000001001 ,
#685
#686
0#
b0000000000110100 $
b0000000000110110 %
b011 &
1'
1(
b1111111111001001 *
b1111111111111110 +
b1111111111001001 ,
#687
#688
#689
#690
#691
1#
b0000000000100010 $
b0000000001001111 %
b101 &
0'
0(
b1111010101011111 *
b1111010101011111 +
b0000000000100000 ,
#692
#693
b0000000001000001 $
b0000000000001001 %
b1111110101110101 *
b1111110101110101 +
b0000000001000000 ,
#694
#695
#696
#697
#698
b0000000000010101 $
b0000000000100110 %
b111 &
b0000000000010111 *
b0000000000010111 +
b1111111111101010 ,
#699
#700
#701
#702
#703
#704
#705
b0000000001001100 $
b0000000001010001 %
b100 &
b0001100000001011 *
b0001100000001011 +
b0000000000011101 ,
#706
#707
#708
b0000000000000000 $
b0000000000110000 %
b000 &
b0000000000000001 *
b0000000000000001 +
b0000000000000000 ,
#709
#710
#711
#712
#713
#714
b0000000000001100 $
b0000000000010001 %
b110 &
b0000000000011001 *
b0000000000011001 +
b1111111111101110 ,
#715
#716
b0000000001000000 $
b0000000000100010 %
b101 &
1'
b0000000001000000 *
b1111011100111111 +
b0000000001000000 ,
#717
0#
b0000000000010100 $
b0000000000010110 %
b100 &
b0000000000000010 *
b0000000110110111 +
b0000000000000010 ,
#718
1#
b0000000000011010 $
b0000000000111011 %
b110 &
b1111111111011110 *
b0000000000110101 +
b1111111111011110 ,
#719
#720
#721
0#
b0000000000110100 $
b0000000001000110 %
b001 &
b1111111111111011 *
b0000000000110011 +
b1111111111111011 ,
#722
b0000000001011111 $
b0000000001001000 %
b000 &
b0000000001001000 *
b0000000000000001 +
b0000000001001000 ,
#723
#724
b0000000000100110 $
b0000000000000100 %
b100 &
b0000000000100010 *
b0000000010010111 +
b0000000000100010 ,
#725
#726
#727
#728
1#
b0000000001011001 $
b0000000001100011 %
b010 &
0'
b0000000010111101 *
b0000000010111101 +
b0000000001111011 ,
#729
b0000000000011000 $
b0000000000010101 %
b111 &
b0000000000011010 *
b0000000000011010 +
b1111111111100111 ,
#730
#731
#732
#733
#734
#735
#736
#737
#738
#739
#740
#741
#742
#743
#744
#745
#746
#747
#748
#749
0#
b0000000000110100 $
b0000000000010010 %
b010 &
b0000000001000110 *
b0000000001000110 +
b0000000000110110 ,
#750
#751
#752
1#
b0000000000001110 $
b0000000000101100 %
b110 &
b0000000000011101 *
b0000000000011101 +
b1111111111011111 ,
#753
#754
b0000000000001010 $
b0000000000110111 %
1'
b1111111111001010 *
b0000000000010101 +
b1111111111001010 ,
#755
#756
#757
#758
#759
#760
#761
#762
#763
0#
b0000000001100010 $
b0000000000000001 %
b011 &
b1111111110011100 *
b0000000001100001 +
b1111111110011100 ,
#764
#765
#766
#767
#768
#769
#770
#771
#772
#773
1#
b0000000000000101 $
b0000000001000001 %
1(
b1111111110111010 *
b1111111111000011 +
b1111111110111010 ,
#774
0#
b0000000001010110 $
b0000000000010110 %
b001 &
0(
b1111111111101001 *
b0000000001010101 +
b1111111111101001 ,
#775
1#
b0000000000110010 $
b0000000001100000 %
b101 &
b0000000000010010 *
b1110110100001101 +
b0000000000010010 ,
#776
#777
#778
#779
#780
0#
b0000000000001110 $
b0000000001100010 %
b010 &
0'
b0000000001110000 *
b0000000001110000 +
b0000000001101110 ,
#781
#782
#783
#784
#785
#786
#787
#788
b0000000000000111 $
b0000000000000010 %
b000 &
1'
b0000000000000010 *
b0000000000000001 +
b0000000000000010 ,
#789
#790
#791
1#
b0000000001010011 $
b0000000000001001 %
b011 &
0'
b0000000001001001 *
b0000000001001001 +
b1111111110100100 ,
#792
#793
#794
#795
0#
b0000000000011011 $
b0000000001011010 %
b000 &
b0000000000000001 *
b0000000000000001 +
b0000000000011010 ,
#796
#797
b0000000001011010 $
b0000000000111010 %
b010 &
b0000000010010100 *
b0000000010010100 +
b0000000001111010 ,
#798
#799
#800
#801
#802
#803
#804
#805
#806
b0000000001010011 $
b0000000000110011 %
b111 &
b0000000001010100 *
b0000000001010100 +
b1111111110101100 ,
#807
#808
#809
#810
1#
b0000000000101100 $
b0000000000010001 %
1'
b1111111111010011 *
b0000000000101110 +
b1111111111010011 ,
#811
#812
#813
#814
#815
0#
b0000000000111110 $
b0000000000001011 %
b101 &
b0000000000110100 *
b1111110100010111 +
b0000000000110100 ,
#816
#817
#818
b0000000001011110 $
b0000000001000110 %
b110 &
0'
b0000000010111100 *
b0000000010111100 +
b1111111111111111 ,
#819
#820
#821
#822
b0000000000000110 $
b0000000000111001 %
b100 &
b0000000101010101 *
b0000000101010101 +
b0000000000111111 ,
#823
1#
b0000000000111110 $
b0000000001010101 %
b000 &
b0000000000000001 *
b0000000000000001 +
b0000000000010100 ,
#824
#825
#826
#827
#828
#829
b0000000000010000 $
b0000000000111000 %
b111 &
1'
b1111111111101111 *
b0000000000010010 +
b1111111111101111 ,
#830
#831
b0000000000011010 $
b0000000001011001 %
b011 &
1(
b1111111110100100 *
b1111111111000000 +
b1111111110100100 ,
#832
#833
b0000000000111010 $
b0000000000011011 %
b010 &
0(
b0000000000111011 *
b0000000001010110 +
b0000000000111011 ,
#834
#835
#836
b0000000001001110 $
b0000000001000011 %
b001 &
0'
b0000000001001100 *
b0000000001001100 +
b1111111110111101 ,
#837
#838
#839
#840
b0000000000011100 $
b0000000000111010 %
b010 &
b0000000001010111 *
b0000000001010111 +
b0000000000111110 ,
#841
#842
#843
#844
#845
#846
b0000000000011000 $
b0000000000100001 %
b001 &
b0000000000010110 *
b0000000000010110 +
b1111111111111111 ,
#847
#848
#849
#850
#851
#852
b0000000000110101 $
b0000000000000011 %
b101 &
1'
b0000000000110100 *
b1111111100101011 +
b0000000000110100 ,
#853
#854
b0000000001010100 $
b0000000000101101 %
b011 &
0'
b0000000000100110 *
b0000000000100110 +
b1111111110000010 ,
#855
0#
b0000000001011001 $
b0000000001010010 %
b100 &
b0001110010000001 *
b0001110010000001 +
b0000000000001011 ,
#856
#857
#858
#859
#860
1#
b0000000000011001 $
b0000000001100010 %
b101 &
1'
b0000000000011001 *
b1111011001010100 +
b0000000000011001 ,
#861
#862
#863
